capture/__init__.py
capture/client.py
capture/eventsource.py
capture/threads.py
capture/lib/__init__.py
capture/lib/exceptions.py
capture/lib/objects.py
capture.py-1.0.0.2.dist-info/LICENSE
capture.py-1.0.0.2.dist-info/METADATA
capture.py-1.0.0.2.dist-info/WHEEL
capture.py-1.0.0.2.dist-info/top_level.txt
capture.py-1.0.0.2.dist-info/RECORD
