Metadata-Version: 2.1
Name: capture.py
Version: 1.0.0.2
Summary: Capture chat app Bots with python!
Home-page: https://github.com/SirLez
Author: SirLez
Author-email: SirLezDV@gmail.com
License: MIT
Download-URL: https://github.com/SirLez/capture.py/archive/refs/heads/main.zip
Keywords: capture,capture.py,capture.chat,capture-chat,captureS,capture-bot,capture-chat,capture-lib,cptr,cptr.co,SirLez,sirlez,srlz,SrLz,api,python,python3,python3.x,api,python,python3,python3.x
Platform: UNKNOWN
Requires-Dist: requests
Requires-Dist: sseclient (==0.0.6)
